sentimentarcs/__init__.py
sentimentarcs/channel.py
sentimentarcs-0.0.4.dist-info/LICENSE
sentimentarcs-0.0.4.dist-info/METADATA
sentimentarcs-0.0.4.dist-info/WHEEL
sentimentarcs-0.0.4.dist-info/top_level.txt
sentimentarcs-0.0.4.dist-info/RECORD
