Metadata-Version: 2.1
Name: sentimentarcs
Version: 0.0.4
Summary: Sentiment Analysis Time Series over Long Texts or Corpora
Home-page: https://github.com/jon-chun/sentimentarcs
Author: Jon Chun
Author-email: jonchun@outlook.com
License: UNKNOWN
Project-URL: Bug Tracker, https://github.com/jon-chun/sentimentarcs/issues
Platform: UNKNOWN
Classifier: Programming Language :: Python :: 3
Classifier: License :: OSI Approved :: MIT License
Classifier: Operating System :: OS Independent
Requires-Python: >=3.6
License-File: LICENSE
